keyrings/envvars/__init__.py
keyrings/envvars/credential.py
keyrings/envvars/keyring.py
keyrings/envvars/py.typed
keyrings/envvars/tests/__init__.py
keyrings/envvars/tests/conftest.py
keyrings/envvars/tests/keyring_test.py
keyrings/envvars/tests/keyrings_envvars_test.py
keyrings_envvars-2.0.0.dist-info/LICENSE
keyrings_envvars-2.0.0.dist-info/METADATA
keyrings_envvars-2.0.0.dist-info/WHEEL
keyrings_envvars-2.0.0.dist-info/entry_points.txt
keyrings_envvars-2.0.0.dist-info/RECORD
