Metadata-Version: 2.3
Name: keyrings.envvars
Version: 2.0.0
Summary: keyring backend plugin to retrieve credentials from environment variables.
License: MIT
Author: wwuck
Author-email: <wirelessduck+py@gmail.com>
Requires-Python: >=3.9.0
Classifier: Development Status :: 5 - Production/Stable
Classifier: License :: OSI Approved :: MIT License
Classifier: Programming Language :: Python :: 3
Classifier: Typing :: Typed
Requires-Dist: keyring (>=23.4.0)
Project-URL: Documentation, https://codeberg.org/wwuck/keyrings.envvars
Project-URL: Repository, https://codeberg.org/wwuck/keyrings.envvars
Project-URL: Tracker, https://codeberg.org/wwuck/keyrings.envvars/issues
